{
    "mapwidth": "1300",
    "mapheight": "700",
    "categories": [],
    "levels": [{
        "id": "basement-floor",
        "title": "Johor",
        "map": "assets/images/mall/johor.svg",
        "minimap": "",
        "locations": [{
                "id": "9999",
                "title": "Food Court",
                "about": "",
                "description": "",
                "category": "",
                "thumbnail": "",
                "x": "0.4303",
                "y": "0.6702",
                "cx": "520",
                "cy": "430"
            }, {
                "id": "500",
                "title": "Starbucks Coffee",
                "about": "Suite 500",
                "description": "Suite 500",
                "category": "food",
                "thumbnail": "",
                "x": "0.2783",
                "y": "0.2202",
                "cx": "325",
                "cy": "110"
            }, {
                "id": "foodstalls",
                "title": "Food Court",
                "about": "Suite 500",
                "description": "Suite 500",
                "category": "food",
                "thumbnail": "",
                "x": "0.2783",
                "y": "0.2202",
                "cx": "325",
                "cy": "110"
            },
            {
                "id": "502",
                "title": "Baskin-Robbins",
                "about": "test",
                "description": "Suite 502",
                "category": "food",
                "thumbnail": "",
                "x": "0.2903",
                "y": "0.2302",
                "cx": "343",
                "cy": "115"
            },
            {
                "id": "506",
                "title": "Camel Active (Opening Soon)",
                "about": "",
                "description": "Suite 506",
                "category": "misc",
                "thumbnail": "",
                "x": "0.3153",
                "y": "0.2302",
                "cx": "375",
                "cy": "115"
            },
            {
                "id": "510",
                "title": "Cotton On",
                "about": "",
                "description": "Suite 510",
                "category": "clothing",
                "thumbnail": "",
                "x": "0.3303",
                "y": "0.2302",
                "cx": "400",
                "cy": "120"
            },
            {
                "id": "514",
                "title": "Bath & Body Works",
                "about": "",
                "description": "Suite 514",
                "category": "clothing",
                "thumbnail": "",
                "x": "0.3603",
                "y": "0.2402",
                "cx": "425",
                "cy": "130"
            },
            {
                "id": "516",
                "title": "Austin Reed",
                "about": "",
                "description": "Suite 516",
                "category": "clothing",
                "thumbnail": "",
                "x": "0.3703",
                "y": "0.2582",
                "cx": "440",
                "cy": "135"
            },
            {
                "id": "518",
                "title": "Obermain",
                "about": "",
                "description": "Suite 518",
                "category": "clothing",
                "thumbnail": "",
                "x": "0.3803",
                "y": "0.2682",
                "cx": "445",
                "cy": "145"
            },
            {
                "id": "520",
                "title": "New Balance Outlet",
                "about": "",
                "description": "Suite 520",
                "category": "misc",
                "thumbnail": "",
                "x": "0.3903",
                "y": "0.2782",
                "cx": "455",
                "cy": "155"
            },
            {
                "id": "522",
                "title": "The Body Shop Outlet",
                "about": "",
                "description": "Suite 522",
                "category": "misc",
                "thumbnail": "",
                "x": "0.3953",
                "y": "0.2882",
                "cx": "465",
                "cy": "160"
            }, {
                "id": "526",
                "title": "Levi's Outlet Store",
                "about": "",
                "description": "Suite 526",
                "category": "clothing",
                "thumbnail": "",
                "x": "0.4103",
                "y": "0.3082",
                "cx": "495",
                "cy": "180"
            }, {
                "id": "528",
                "title": "Dockers",
                "about": "",
                "description": "Suite 528",
                "category": "clothing",
                "thumbnail": "",
                "x": "0.4303",
                "y": "0.3182",
                "cx": "530",
                "cy": "190"
            },{
                "id": "530",
                "title": "Royal Sporting House (Opening Soon)",
                "about": "",
                "description": "Suite 530",
                "category": "clothing",
                "thumbnail": "",
                "x": "0.4503",
                "y": "0.3052",
                "cx": "530",
                "cy": "190"
            }, {
                "id": "532",
                "title": "Guess",
                "about": "",
                "description": "Suite 532",
                "category": "clothing",
                "thumbnail": "",
                "x": "0.4803",
                "y": "0.3102",
                "cx": "600",
                "cy": "180"
            }, {
                "id": "902",
                "title": "Adidas",
                "about": "",
                "description": "Suite 902",
                "category": "clothing",
                "thumbnail": "",
                "x": "0.5403",
                "y": "0.3202",
                "cx": "670",
                "cy": "180"
            }, {
                "id": "908",
                "title": "Asics",
                "about": "",
                "description": "Suite 908",
                "category": "misc",
                "thumbnail": "",
                "x": "0.5653",
                "y": "0.3202",
                "cx": "710",
                "cy": "180"
            }, {
                "id": "910",
                "title": "Hush Puppies Apparel",
                "about": "",
                "description": "Suite 910",
                "category": "misc",
                "thumbnail": "",
                "x": "0.5803",
                "y": "0.3202",
                "cx": "727",
                "cy": "180"
            }, {
                "id": "912",
                "title": "Xixili",
                "about": "",
                "description": "Suite 912",
                "category": "misc",
                "thumbnail": "",
                "x": "0.5933",
                "y": "0.3202",
                "cx": "750",
                "cy": "180"
            }, {
                "id": "914",
                "title": "Swatch",
                "about": "",
                "description": "Suite 914",
                "category": "misc",
                "thumbnail": "",
                "x": "0.6083",
                "y": "0.3202",
                "cx": "775",
                "cy": "180"
            }, {
                "id": "915",
                "title": "Sunglass Hut",
                "about": "",
                "description": "Suite 915",
                "category": "misc",
                "thumbnail": "",
                "x": "0.6183",
                "y": "0.3102",
                "cx": "790",
                "cy": "170"
            }, {
                "id": "916",
                "title": "Rockport",
                "about": "",
                "description": "Suite 916",
                "category": "misc",
                "thumbnail": "",
                "x": "0.6383",
                "y": "0.3002",
                "cx": "810",
                "cy": "160"
            }, {
                "id": "917",
                "title": "Poney Outlet",
                "about": "",
                "description": "Suite 917",
                "category": "misc",
                "thumbnail": "",
                "x": "0.6403",
                "y": "0.2902",
                "cx": "820",
                "cy": "155"
            }, {
                "id": "918",
                "title": "Hush Puppies",
                "about": "",
                "description": "Suite 918",
                "category": "misc",
                "thumbnail": "",
                "x": "0.6403",
                "y": "0.2702",
                "cx": "827",
                "cy": "145"
            }, {
                "id": "920",
                "title": "Anakku",
                "about": "",
                "description": "Suite 920",
                "category": "misc",
                "thumbnail": "",
                "x": "0.6553",
                "y": "0.2702",
                "cx": "835",
                "cy": "140"
            }, {
                "id": "922",
                "title": "Animation World",
                "about": "",
                "description": "Suite 922",
                "category": "misc",
                "thumbnail": "",
                "x": "0.6603",
                "y": "0.2602",
                "cx": "845",
                "cy": "135"
            }, {
                "id": "1402",
                "title": "TCBY Frozen Yogurt",
                "about": "",
                "description": "Suite 1402",
                "category": "food",
                "thumbnail": "",
                "x": "0.6803",
                "y": "0.2272",
                "cx": "870",
                "cy": "120"
            }, {
                "id": "1000",
                "title": "Nike Factory Store",
                "about": "",
                "description": "Suite 1000",
                "category": "misc",
                "thumbnail": "",
                "x": "0.2203",
                "y": "0.2682",
                "cx": "270",
                "cy": "140"
            }, {
                "id": "1002",
                "title": "Absolute Thai",
                "about": "",
                "description": "Suite 1002",
                "category": "food",
                "thumbnail": "",
                "x": "0.2003",
                "y": "0.3082",
                "cx": "255",
                "cy": "160"
            }, {
                "id": "2000",
                "title": "Taang Shifu",
                "about": "",
                "description": "Suite 2000",
                "category": "food",
                "thumbnail": "",
                "x": "0.2553",
                "y": "0.3202",
                "cx": "290",
                "cy": "165"
            }, {
                "id": "400",
                "title": "Renoma Paris",
                "about": "",
                "description": "Suite 400",
                "category": "misc",
                "thumbnail": "",
                "x": "0.2653",
                "y": "0.2702",
                "cx": "315",
                "cy": "128"
            }, {
                "id": "401",
                "title": "Crepe & San Churros",
                "about": "",
                "description": "Suite 401",
                "category": "food",
                "thumbnail": "",
                "x": "0.2553",
                "y": "0.2702",
                "cx": "293",
                "cy": "133"
            }, {
                "id": "402",
                "title": "Skechers",
                "about": "",
                "description": "Suite 402",
                "category": "misc",
                "thumbnail": "",
                "x": "0.2753",
                "y": "0.2702",
                "cx": "332",
                "cy": "128"
            }, {
                "id": "406",
                "title": "Puma",
                "about": "",
                "description": "Suite 406",
                "category": "misc",
                "thumbnail": "",
                "x": "0.2953",
                "y": "0.2802",
                "cx": "355",
                "cy": "130"
            }, {
                "id": "408",
                "title": "Carlo Rino",
                "about": "",
                "description": "Suite 408",
                "category": "misc",
                "thumbnail": "",
                "x": "0.3153",
                "y": "0.2802",
                "cx": "383",
                "cy": "135"
            }, {
                "id": "410",
                "title": "Akemi Uchi",
                "about": "",
                "description": "Suite 410",
                "category": "misc",
                "thumbnail": "",
                "x": "0.3253",
                "y": "0.2902",
                "cx": "402",
                "cy": "140"
            }, {
                "id": "412",
                "title": "City Chain",
                "about": "",
                "description": "Suite 412",
                "category": "misc",
                "thumbnail": "",
                "x": "0.3353",
                "y": "0.2902",
                "cx": "412",
                "cy": "145"
            }, {
                "id": "414",
                "title": "Rip Curl",
                "about": "",
                "description": "Suite 414",
                "category": "misc",
                "thumbnail": "",
                "x": "0.3353",
                "y": "0.3102",
                "cx": "430",
                "cy": "150"
            }, {
                "id": "416",
                "title": "G2000 Outlet",
                "about": "",
                "description": "Suite 416",
                "category": "misc",
                "thumbnail": "",
                "x": "0.3453",
                "y": "0.3202",
                "cx": "440",
                "cy": "160"
            }, {
                "id": "418",
                "title": "Time Lab",
                "about": "",
                "description": "Suite 418",
                "category": "misc",
                "thumbnail": "",
                "x": "0.3553",
                "y": "0.3302",
                "cx": "450",
                "cy": "165"
            }, {
                "id": "420",
                "title": "Clarks",
                "about": "",
                "description": "Suite 420",
                "category": "misc",
                "thumbnail": "",
                "x": "0.3653",
                "y": "0.3502",
                "cx": "468",
                "cy": "180"
            }, {
                "id": "424",
                "title": "Esprit",
                "about": "",
                "description": "Suite 424",
                "category": "misc",
                "thumbnail": "",
                "x": "0.3853",
                "y": "0.3702",
                "cx": "482",
                "cy": "192"
            }, {
                "id": "426",
                "title": "La Senza Lingerie",
                "about": "",
                "description": "Suite 426",
                "category": "misc",
                "thumbnail": "",
                "x": "0.4103",
                "y": "0.3802",
                "cx": "505",
                "cy": "200"
            }, {
                "id": "428",
                "title": "Fossil",
                "about": "",
                "description": "Suite 428",
                "category": "misc",
                "thumbnail": "",
                "x": "0.4253",
                "y": "0.3802",
                "cx": "525",
                "cy": "198"
            }, {
                "id": "430",
                "title": "Lacoste Outlet",
                "about": "",
                "description": "Suite 430",
                "category": "misc",
                "thumbnail": "",
                "x": "0.4403",
                "y": "0.3802",
                "cx": "545",
                "cy": "198"
            }, {
                "id": "432",
                "title": "DKNY",
                "about": "",
                "description": "Suite 432",
                "category": "misc",
                "thumbnail": "",
                "x": "0.4553",
                "y": "0.3702",
                "cx": "565",
                "cy": "198"
            }, {
                "id": "434",
                "title": "CK Calvin Klein",
                "about": "",
                "description": "Suite 434",
                "category": "misc",
                "thumbnail": "",
                "x": "0.4703",
                "y": "0.3702",
                "cx": "585",
                "cy": "198"
            }, {
                "id": "436",
                "title": "Armani Exchange",
                "about": "",
                "description": "Suite 436",
                "category": "misc",
                "thumbnail": "",
                "x": "0.4903",
                "y": "0.3702",
                "cx": "610",
                "cy": "200"
            }, {
                "id": "801",
                "title": "Ace Bags & Luggage",
                "about": "",
                "description": "Suite 801",
                "category": "misc",
                "thumbnail": "",
                "x": "0.5650",
                "y": "0.3852",
                "cx": "690",
                "cy": "200"
            }, {
                "id": "804",
                "title": "Polo Ralph Lauren Children",
                "about": "",
                "description": "Suite 804",
                "category": "misc",
                "thumbnail": "",
                "x": "0.5803",
                "y": "0.3852",
                "cx": "720",
                "cy": "200"
            }, {
                "id": "806",
                "title": "Aerosoles",
                "about": "",
                "description": "Suite 806",
                "category": "misc",
                "thumbnail": "",
                "x": "0.5903",
                "y": "0.3852",
                "cx": "740",
                "cy": "200"
            }, {
                "id": "808",
                "title": "Timberland",
                "about": "",
                "description": "Suite 808",
                "category": "misc",
                "thumbnail": "",
                "x": "0.6203",
                "y": "0.3852",
                "cx": "770",
                "cy": "200"
            }, {
                "id": "812",
                "title": "Converse",
                "about": "",
                "description": "Suite 812",
                "category": "misc",
                "thumbnail": "",
                "x": "0.6503",
                "y": "0.3852",
                "cx": "795",
                "cy": "190"
            }, {
                "id": "814",
                "title": "Aldo",
                "about": "",
                "description": "Suite 814",
                "category": "misc",
                "thumbnail": "",
                "x": "0.6603",
                "y": "0.3652",
                "cx": "810",
                "cy": "184"
            }, {
                "id": "816",
                "title": "Hang Ten",
                "about": "",
                "description": "Suite 816",
                "category": "misc",
                "thumbnail": "",
                "x": "0.6703",
                "y": "0.3402",
                "cx": "830",
                "cy": "170"
            }, {
                "id": "818",
                "title": "Sembonia",
                "about": "",
                "description": "Suite 818",
                "category": "misc",
                "thumbnail": "",
                "x": "0.6803",
                "y": "0.3302",
                "cx": "840",
                "cy": "165"
            }, {
                "id": "820",
                "title": "Rubi Shoes",
                "about": "",
                "description": "Suite 820",
                "category": "misc",
                "thumbnail": "",
                "x": "0.6903",
                "y": "0.3252",
                "cx": "850",
                "cy": "158"
            }, {
                "id": "822",
                "title": "Leather Avenue",
                "about": "",
                "description": "Suite 822",
                "category": "misc",
                "thumbnail": "",
                "x": "0.6953",
                "y": "0.3152",
                "cx": "860",
                "cy": "152"
            }, {
                "id": "824",
                "title": "Cotton On Kids",
                "about": "",
                "description": "Suite 824",
                "category": "misc",
                "thumbnail": "",
                "x": "0.7103",
                "y": "0.3052",
                "cx": "865",
                "cy": "147"
            }, {
                "id": "825",
                "title": "Stride Rite",
                "about": "",
                "description": "Suite 825",
                "category": "misc",
                "thumbnail": "",
                "x": "0.7023",
                "y": "0.2952",
                "cx": "875",
                "cy": "140"
            }, {
                "id": "1302",
                "title": "Soda",
                "about": "",
                "description": "Suite 1302",
                "category": "misc",
                "thumbnail": "",
                "x": "0.7153",
                "y": "0.2802",
                "cx": "885",
                "cy": "132"
            }, {
                "id": "1304",
                "title": "Voir Gallery",
                "about": "",
                "description": "Suite 1304",
                "category": "misc",
                "thumbnail": "",
                "x": "0.7253",
                "y": "0.2802",
                "cx": "895",
                "cy": "127"
            }, {
                "id": "1306",
                "title": "Diadora",
                "about": "",
                "description": "Suite 1306",
                "category": "misc",
                "thumbnail": "",
                "x": "0.7253",
                "y": "0.2672",
                "cx": "905",
                "cy": "122"
            }, {
                "id": "1202",
                "title": "Akemi Uchi Galleria",
                "about": "",
                "description": "Suite 1202",
                "category": "misc",
                "thumbnail": "",
                "x": "0.7403",
                "y": "0.3652",
                "cx": "940",
                "cy": "210"
            }, {
                "id": "724",
                "title": "Jim Thompson",
                "about": "",
                "description": "Suite 724",
                "category": "misc",
                "thumbnail": "",
                "x": "0.7203",
                "y": "0.4002",
                "cx": "925",
                "cy": "235"
            }, {
                "id": "722",
                "title": "Chocolat 5D Studio",
                "about": "",
                "description": "Suite 722",
                "category": "misc",
                "thumbnail": "",
                "x": "0.7003",
                "y": "0.4202",
                "cx": "915",
                "cy": "245"
            }, {
                "id": "720",
                "title": "La Perla",
                "about": "",
                "description": "Suite 720",
                "category": "misc",
                "thumbnail": "",
                "x": "0.7103",
                "y": "0.4302",
                "cx": "905",
                "cy": "250"
            }, {
                "id": "718",
                "title": "Lululemon",
                "about": "",
                "description": "Suite 718",
                "category": "misc",
                "thumbnail": "",
                "x": "0.6953",
                "y": "0.4402",
                "cx": "895",
                "cy": "260"
            }, {
                "id": "716",
                "title": "Beauty Scents",
                "about": "",
                "description": "Suite 716",
                "category": "misc",
                "thumbnail": "",
                "x": "0.6853",
                "y": "0.4452",
                "cx": "885",
                "cy": "270"
            }, {
                "id": "714",
                "title": "Calvin Klein Underwear",
                "about": "",
                "description": "Suite 714",
                "category": "misc",
                "thumbnail": "",
                "x": "0.6653",
                "y": "0.4652",
                "cx": "865",
                "cy": "290"
            }, {
                "id": "712",
                "title": "Calvin Klein Jeans",
                "about": "",
                "description": "Suite 712",
                "category": "misc",
                "thumbnail": "",
                "x": "0.6553",
                "y": "0.4852",
                "cx": "845",
                "cy": "295"
            }, {
                "id": "708",
                "title": "Sacoor Outlet",
                "about": "",
                "description": "Suite 708",
                "category": "misc",
                "thumbnail": "",
                "x": "0.6253",
                "y": "0.4952",
                "cx": "805",
                "cy": "305"
            }, {
                "id": "706",
                "title": "Swarovski",
                "about": "",
                "description": "Suite 706",
                "category": "misc",
                "thumbnail": "",
                "x": "0.5953",
                "y": "0.5052",
                "cx": "750",
                "cy": "310"
            }, {
                "id": "704",
                "title": "Furla",
                "about": "",
                "description": "Suite 704",
                "category": "misc",
                "thumbnail": "",
                "x": "0.5803",
                "y": "0.5052",
                "cx": "725",
                "cy": "310"
            }, {
                "id": "701",
                "title": "Versace",
                "about": "",
                "description": "Suite 701",
                "category": "misc",
                "thumbnail": "",
                "x": "0.5443",
                "y": "0.5052",
                "cx": "690",
                "cy": "310"
            }, {
                "id": "702",
                "title": "Jimmy Choo",
                "about": "",
                "description": "Suite 702",
                "category": "misc",
                "thumbnail": "",
                "x": "0.5603",
                "y": "0.5052",
                "cx": "710",
                "cy": "310"
            }, {
                "id": "700",
                "title": "700",
                "about": "",
                "description": "Suite 700",
                "category": "misc",
                "thumbnail": "",
                "x": "0.5303",
                "y": "0.5052",
                "cx": "660",
                "cy": "310"
            }, {
                "id": "338",
                "title": "Armani Outlet",
                "about": "",
                "description": "Suite 338",
                "category": "misc",
                "thumbnail": "",
                "x": "0.4603",
                "y": "0.5002",
                "cx": "575",
                "cy": "320"
            }, {
                "id": "334",
                "title": "Blackbarrett",
                "about": "",
                "description": "Suite 334",
                "category": "misc",
                "thumbnail": "",
                "x": "0.4303",
                "y": "0.5002",
                "cx": "535",
                "cy": "320"
            }, {
                "id": "332",
                "title": "Salvatore Ferragamo Company Store",
                "about": "",
                "description": "Suite 332",
                "category": "misc",
                "thumbnail": "",
                "x": "0.4103",
                "y": "0.5002",
                "cx": "500",
                "cy": "320"
            }, {
                "id": "328",
                "title": "Tory Burch",
                "about": "",
                "description": "Suite 328",
                "category": "misc",
                "thumbnail": "",
                "x": "0.3803",
                "y": "0.5002",
                "cx": "460",
                "cy": "320"
            }, {
                "id": "326",
                "title": "Swiss Watch Gallery",
                "about": "",
                "description": "Suite 326",
                "category": "misc",
                "thumbnail": "",
                "x": "0.3603",
                "y": "0.5002",
                "cx": "430",
                "cy": "310"
            }, {
                "id": "322",
                "title": "Tumi",
                "about": "",
                "description": "Suite 322",
                "category": "misc",
                "thumbnail": "",
                "x": "0.3403",
                "y": "0.4802",
                "cx": "395",
                "cy": "295"
            }, {
                "id": "320",
                "title": "Wear & When",
                "about": "",
                "description": "Suite 320",
                "category": "misc",
                "thumbnail": "",
                "x": "0.3303",
                "y": "0.4702",
                "cx": "385",
                "cy": "280"
            }, {
                "id": "318",
                "title": "Royal Selangor",
                "about": "",
                "description": "Suite 318",
                "category": "misc",
                "thumbnail": "",
                "x": "0.3203",
                "y": "0.4402",
                "cx": "370",
                "cy": "265"
            }, {
                "id": "316",
                "title": "Geox",
                "about": "",
                "description": "Suite 316",
                "category": "misc",
                "thumbnail": "",
                "x": "0.3103",
                "y": "0.4302",
                "cx": "360",
                "cy": "255"
            }, {
                "id": "314",
                "title": "Oroton Factory",
                "about": "",
                "description": "Suite 314",
                "category": "misc",
                "thumbnail": "",
                "x": "0.3103",
                "y": "0.4102",
                "cx": "350",
                "cy": "245"
            }, {
                "id": "312",
                "title": "Bonia",
                "about": "",
                "description": "Suite 312",
                "category": "misc",
                "thumbnail": "",
                "x": "0.2903",
                "y": "0.4002",
                "cx": "340",
                "cy": "240"
            }, {
                "id": "310",
                "title": "Samsonite Factory Outlet",
                "about": "",
                "description": "Suite 310",
                "category": "misc",
                "thumbnail": "",
                "x": "0.2803",
                "y": "0.3902",
                "cx": "325",
                "cy": "230"
            }, {
                "id": "308",
                "title": "Universal Traveller",
                "about": "",
                "description": "Suite 308",
                "category": "misc",
                "thumbnail": "",
                "x": "0.2603",
                "y": "0.3902",
                "cx": "305",
                "cy": "230"
            }, {
                "id": "306",
                "title": "Tomei",
                "about": "",
                "description": "Suite 306",
                "category": "misc",
                "thumbnail": "",
                "x": "0.2503",
                "y": "0.3802",
                "cx": "285",
                "cy": "230"
            }, {
                "id": "304",
                "title": "Pedro Outlet",
                "about": "",
                "description": "Suite 304",
                "category": "misc",
                "thumbnail": "",
                "x": "0.2323",
                "y": "0.3802",
                "cx": "265",
                "cy": "225"
            }, {
                "id": "302",
                "title": "Cosmetics & Designer Fragrances",
                "about": "",
                "description": "Suite 302",
                "category": "misc",
                "thumbnail": "",
                "x": "0.2223",
                "y": "0.3702",
                "cx": "245",
                "cy": "225"
            }, {
                "id": "300",
                "title": "Vincci",
                "about": "",
                "description": "Suite 300",
                "category": "misc",
                "thumbnail": "",
                "x": "0.2003",
                "y": "0.3702",
                "cx": "225",
                "cy": "215"
            }, {
                "id": "100",
                "title": "Padini Outlet Store",
                "about": "",
                "description": "Suite 100",
                "category": "misc",
                "thumbnail": "",
                "x": "0.1603",
                "y": "0.3952",
                "cx": "205",
                "cy": "225"
            }, {
                "id": "104",
                "title": "Suria Muhabat Money Changer",
                "about": "",
                "description": "Suite 104",
                "category": "misc",
                "thumbnail": "",
                "x": "0.1403",
                "y": "0.4302",
                "cx": "160",
                "cy": "255"
            }, {
                "id": "1106",
                "title": "World of Outdoors",
                "about": "",
                "description": "Suite 1106",
                "category": "misc",
                "thumbnail": "",
                "x": "0.7903",
                "y": "0.4152",
                "cx": "985",
                "cy": "245"
            }, {
                "id": "1104",
                "title": "Columbia",
                "about": "",
                "description": "Suite 1104",
                "category": "misc",
                "thumbnail": "",
                "x": "0.8003",
                "y": "0.4352",
                "cx": "1000",
                "cy": "255"
            }, {
                "id": "1102",
                "title": "The Flexx",
                "about": "",
                "description": "Suite 1102",
                "category": "misc",
                "thumbnail": "",
                "x": "0.8103",
                "y": "0.4552",
                "cx": "1020",
                "cy": "265"
            }, {
                "id": "633",
                "title": "Dome Café",
                "about": "",
                "description": "Suite 633",
                "category": "food",
                "thumbnail": "",
                "x": "0.7903",
                "y": "0.4852",
                "cx": "975",
                "cy": "250"
            }, {
                "id": "632",
                "title": "Aigner",
                "about": "",
                "description": "Suite 632",
                "category": "misc",
                "thumbnail": "",
                "x": "0.7703",
                "y": "0.4652",
                "cx": "955",
                "cy": "260"
            }, {
                "id": "630",
                "title": "Hackett London",
                "about": "",
                "description": "Suite 630",
                "category": "misc",
                "thumbnail": "",
                "x": "0.7603",
                "y": "0.4852",
                "cx": "940",
                "cy": "270"
            }, {
                "id": "628",
                "title": "Seen",
                "about": "",
                "description": "Suite 628",
                "category": "misc",
                "thumbnail": "",
                "x": "0.7503",
                "y": "0.4952",
                "cx": "952",
                "cy": "275"
            }, {
                "id": "626",
                "title": "Optical 88",
                "about": "",
                "description": "Suite 626",
                "category": "misc",
                "thumbnail": "",
                "x": "0.7403",
                "y": "0.5052",
                "cx": "910",
                "cy": "285"
            }, {
                "id": "624",
                "title": "Watch Station International",
                "about": "",
                "description": "Suite 624",
                "category": "misc",
                "thumbnail": "",
                "x": "0.7203",
                "y": "0.5252",
                "cx": "890",
                "cy": "298"
            }, {
                "id": "622",
                "title": "Boggi Milano (Opening Soon)",
                "about": "",
                "description": "Suite 622",
                "category": "misc",
                "thumbnail": "",
                "x": "0.7103",
                "y": "0.5252",
                "cx": "875",
                "cy": "308"
            }, {
                "id": "620",
                "title": "The Make Up Outlet",
                "about": "",
                "description": "Suite 620",
                "category": "misc",
                "thumbnail": "",
                "x": "0.7103",
                "y": "0.5652",
                "cx": "865",
                "cy": "322"
            }, {
                "id": "616",
                "title": "Kate Spade New York",
                "about": "",
                "description": "Suite 616",
                "category": "misc",
                "thumbnail": "",
                "x": "0.6803",
                "y": "0.5852",
                "cx": "840",
                "cy": "330"
            }, {
                "id": "612",
                "title": "Hugo Boss",
                "about": "",
                "description": "Suite 612",
                "category": "misc",
                "thumbnail": "",
                "x": "0.6403",
                "y": "0.5952",
                "cx": "800",
                "cy": "335"
            }, {
                "id": "610",
                "title": "Coach Men's",
                "about": "",
                "description": "Suite 610",
                "category": "misc",
                "thumbnail": "",
                "x": "0.6153",
                "y": "0.5952",
                "cx": "760",
                "cy": "330"
            }, {
                "id": "606",
                "title": "Ermenegildo Zegna Outlet Store",
                "about": "",
                "description": "Suite 606",
                "category": "misc",
                "thumbnail": "",
                "x": "0.5403",
                "y": "0.6152",
                "cx": "655",
                "cy": "345"
            }, {
                "id": "604",
                "title": "Polo Ralph Lauren",
                "about": "",
                "description": "Suite 604",
                "category": "misc",
                "thumbnail": "",
                "x": "0.5803",
                "y": "0.5952",
                "cx": "710",
                "cy": "330"
            }, {
                "id": "602",
                "title": "Maybank",
                "about": "",
                "description": "Suite 602",
                "category": "misc",
                "thumbnail": "",
                "x": "0.5403",
                "y": "0.6652",
                "cx": "655",
                "cy": "410"
            }, {
                "id": "600",
                "title": "Police Base",
                "about": "",
                "description": "Suite 600",
                "category": "misc",
                "thumbnail": "",
                "x": "0.5453",
                "y": "0.6952",
                "cx": "655",
                "cy": "430"
            }, {
                "id": "238",
                "title": "Gucci",
                "about": "",
                "description": "Suite 238",
                "category": "misc",
                "thumbnail": "",
                "x": "0.4703",
                "y": "0.6602",
                "cx": "595",
                "cy": "405"
            }, {
                "id": "232",
                "title": "Michael Kors",
                "about": "",
                "description": "Suite 232",
                "category": "misc",
                "thumbnail": "",
                "x": "0.4503",
                "y": "0.5702",
                "cx": "585",
                "cy": "335"
            }, {
                "id": "230",
                "title": "Coach",
                "about": "",
                "description": "Suite 230",
                "category": "misc",
                "thumbnail": "",
                "x": "0.4003",
                "y": "0.5702",
                "cx": "500",
                "cy": "335"
            }, {
                "id": "222",
                "title": "Bally",
                "about": "",
                "description": "Suite 222",
                "category": "misc",
                "thumbnail": "",
                "x": "0.3303",
                "y": "0.5702",
                "cx": "415",
                "cy": "330"
            }, {
                "id": "220",
                "title": "Brooks Brothers Factory Store",
                "about": "",
                "description": "Suite 220",
                "category": "misc",
                "thumbnail": "",
                "x": "0.3103",
                "y": "0.5602",
                "cx": "400",
                "cy": "322"
            }, {
                "id": "218",
                "title": "Tommy Hilfiger",
                "about": "",
                "description": "Suite 218",
                "category": "misc",
                "thumbnail": "",
                "x": "0.2903",
                "y": "0.5402",
                "cx": "380",
                "cy": "310"
            }, {
                "id": "214",
                "title": "Kipling",
                "about": "",
                "description": "Suite 214",
                "category": "misc",
                "thumbnail": "",
                "x": "0.2803",
                "y": "0.5102",
                "cx": "360",
                "cy": "290"
            }, {
                "id": "212",
                "title": "Victoria's Secret",
                "about": "",
                "description": "Suite 212",
                "category": "misc",
                "thumbnail": "",
                "x": "0.2703",
                "y": "0.4902",
                "cx": "345",
                "cy": "275"
            }, {
                "id": "210",
                "title": "The Cosmetics Company Store",
                "about": "",
                "description": "Suite 210",
                "category": "misc",
                "thumbnail": "",
                "x": "0.2603",
                "y": "0.4702",
                "cx": "335",
                "cy": "265"
            }, {
                "id": "208",
                "title": "Braun Buffel",
                "about": "",
                "description": "Suite 208",
                "category": "misc",
                "thumbnail": "",
                "x": "0.2503",
                "y": "0.4602",
                "cx": "305",
                "cy": "255"
            }, {
                "id": "206",
                "title": "Fidani Chocolate",
                "about": "",
                "description": "Suite 206",
                "category": "misc",
                "thumbnail": "",
                "x": "0.2403",
                "y": "0.4502",
                "cx": "285",
                "cy": "245"
            }, {
                "id": "204",
                "title": "George & Dragon Café",
                "about": "",
                "description": "Suite 204",
                "category": "food",
                "thumbnail": "",
                "x": "0.2203",
                "y": "0.4502",
                "cx": "260",
                "cy": "243"
            }, {
                "id": "200",
                "title": "The Coffee Bean & Tea Leaf",
                "about": "",
                "description": "Suite 200",
                "category": "food",
                "thumbnail": "",
                "x": "0.1903",
                "y": "0.4502",
                "cx": "220",
                "cy": "245"
            }

        ]
    }]
}